{
  "id": "18RdkSv9h9",
  "or_id": "18RdkSv9h9",
  "title": "FINALLY: fast and universal speech enhancement with studio-like quality",
  "title_zh": "",
  "authors": [
    "Nicholas Babaev",
    "Kirill Tamogashev",
    "Azat Saginbaev",
    "Ivan Shchekotov",
    "Hanbin Bae",
    "Hosang Sung",
    "WonJun Lee",
    "Hoon-Young Cho",
    "Pavel Andreev"
  ],
  "conference": "NeurIPS",
  "year": 2024,
  "venue": "NeurIPS 2024 poster",
  "abstract": "In this paper, we address the challenge of speech enhancement in real-world recordings, which often contain various forms of distortion, such as background noise, reverberation, and microphone artifacts.\nWe revisit the use of Generative Adversarial Networks (GANs) for speech enhancement and theoretically show that GANs are naturally inclined to seek the point of maximum density within the conditional clean speech distribution, which, as we argue, is essential for speech enhancement task.\nWe study various feature extractors for perceptual loss to facilitate the stability of adversarial training, developing a methodology for probing the structure of the feature space.\nThis leads us to integrate WavLM-based perceptual loss into MS-STFT adversarial training pipeline, creating an effective and stable training procedure for the speech enhancement model.\nThe resulting speech enhancement model, which we refer to as FINALLY, builds upon the HiFi++ architecture, augmented with a WavLM encoder and a novel training pipeline.\nEmpirical results on various datasets confirm our model's ability to produce clear, high-quality speech at 48 kHz, achieving state-of-the-art performance in the field of speech enhancement. Demo page: https://samsunglabs.github.io/FINALLY-page/",
  "abstract_zh": "",
  "tldr": "2024 SoTA for speech enhancement",
  "keywords": [
    "speech enhancement; generative models"
  ],
  "links": {
    "openreview": "https://openreview.net/forum?id=18RdkSv9h9",
    "arxiv": null,
    "dblp": null,
    "pdf": "https://openreview.net/pdf/2e3b3e577243cca83d9bdcdcc537a17d24af94b5.pdf"
  },
  "citationCount": 0,
  "isHighQuality": false,
  "sections": {
    "method_summary": "2024 SoTA for speech enhancement"
  },
  "collected_at": "2026-03-08T17:00:23.868Z"
}