{
  "id": "A34sBX4R5N",
  "or_id": "A34sBX4R5N",
  "title": "Optimal Transport-based Labor-free Text Prompt Modeling for Sketch Re-identification",
  "title_zh": "",
  "authors": [
    "Rui Li",
    "Tingting Ren",
    "Jie Wen",
    "Jinxing Li"
  ],
  "conference": "NeurIPS",
  "year": 2024,
  "venue": "NeurIPS 2024 poster",
  "abstract": "Sketch Re-identification (Sketch Re-ID), \nwhich aims to retrieve target person from an image gallery based on a sketch query, is crucial for criminal investigation, law enforcement, and missing person searches. \nExisting methods aim to alleviate the modality gap by employing semantic metrics constraints or auxiliary modal guidance. However, they incur expensive labor costs and inevitably omit fine-grained modality-consistent information due to the abstraction of sketches.\nTo address this issue, this paper proposes a novel $\\textit{Optimal Transport-based Labor-free Text Prompt Modeling}$ (OLTM) network, which hierarchically extracts coarse- and fine-grained similarity representations guided by textual semantic information without any additional annotations. \nSpecifically, multiple target attributes are flexibly obtained by a pre-trained visual question answering (VQA) model. Subsequently, a text prompt reasoning module employs learnable prompt strategy and optimal transport algorithm to extract discriminative global and local text representations, which serve as a bridge for hierarchical and multi-granularity modal alignment between sketch and image modalities.\nAdditionally, instead of measuring the similarity of two samples by only computing their distance, a novel triplet assignment loss is further proposed, in which the whole data distribution also contributes to optimizing the inter/intra-class distances. Extensive experiments conducted on two public benchmarks consistently demonstrate the robustness and superiority of our OLTM over state-of-the-art methods.",
  "abstract_zh": "",
  "tldr": "",
  "keywords": [
    "Sketch Re-identification; Optimal Transport; Prompt Learning"
  ],
  "links": {
    "openreview": "https://openreview.net/forum?id=A34sBX4R5N",
    "arxiv": null,
    "dblp": null,
    "pdf": "https://openreview.net/pdf/69740cf0a6edc30cf8f8fd5a38455fb491f0b299.pdf"
  },
  "citationCount": 0,
  "isHighQuality": false,
  "sections": {
    "method_summary": "Sketch Re-identification (Sketch Re-ID), \nwhich aims to retrieve target person from an image gallery based on a sketch query, is crucial for criminal investigation, law enforcement, and missing person searches. \nExisting methods aim to alleviate the modality gap by employing semantic metrics constra"
  },
  "collected_at": "2026-03-07T17:40:48.516Z"
}