{
  "id": "bkLetzd97M",
  "or_id": "bkLetzd97M",
  "title": "OnlineTAS: An Online Baseline for Temporal Action Segmentation",
  "title_zh": "",
  "authors": [
    "Qing Zhong",
    "Guodong Ding",
    "Angela Yao"
  ],
  "conference": "NeurIPS",
  "year": 2024,
  "venue": "NeurIPS 2024 poster",
  "abstract": "Temporal context plays a significant role in temporal action segmentation. In an offline setting, the context is typically captured by the segmentation network after observing the entire sequence. However, capturing and using such context information in an online setting remains an under-explored problem. This work presents the first online framework for temporal action segmentation. At the core of the framework is an adaptive memory designed to accommodate dynamic changes in context over time, alongside a feature augmentation module that enhances the frames with the memory. In addition, we propose a post-processing approach to mitigate the severe over-segmentation in the online setting. On three common segmentation benchmarks, our approach achieves state-of-the-art performance.",
  "abstract_zh": "",
  "tldr": "",
  "keywords": [
    "Temporal Action Segmentation",
    "Video Understanding"
  ],
  "links": {
    "openreview": "https://openreview.net/forum?id=bkLetzd97M",
    "arxiv": null,
    "dblp": null,
    "pdf": "https://openreview.net/pdf/b7b20d7ead281b3abe5e9eceafbe1fe02f7f2267.pdf"
  },
  "citationCount": 0,
  "isHighQuality": false,
  "sections": {
    "method_summary": "Temporal context plays a significant role in temporal action segmentation. In an offline setting, the context is typically captured by the segmentation network after observing the entire sequence. However, capturing and using such context information in an online setting remains an under-explored pr"
  },
  "collected_at": "2026-03-10T20:41:29.385Z"
}