{
  "id": "CFez7MFUFd",
  "or_id": "CFez7MFUFd",
  "title": "Cross-Scale Self-Supervised Blind Image Deblurring via Implicit Neural Representation",
  "title_zh": "",
  "authors": [
    "Tianjing Zhang",
    "Yuhui Quan",
    "Hui Ji"
  ],
  "conference": "NeurIPS",
  "year": 2024,
  "venue": "NeurIPS 2024 poster",
  "abstract": "Blind image deblurring (BID) is an important yet challenging image recovery problem. Most existing deep learning methods require supervised training with ground truth (GT) images. This paper introduces a self-supervised method for BID that does not require GT images. The key challenge is to regularize the training to prevent over-fitting due to the absence of GT images. By leveraging an exact relationship among the blurred image, latent image, and blur kernel across consecutive scales, we propose an effective cross-scale consistency loss. This is implemented by representing the image and kernel with implicit neural representations (INRs), whose resolution-free property enables consistent yet efficient computation for network training across multiple scales. Combined with a progressively coarse-to-fine training scheme, the proposed method significantly outperforms existing self-supervised methods  in extensive experiments.",
  "abstract_zh": "",
  "tldr": "",
  "keywords": [
    "Blind Image Deblurring",
    "Self-Supervised Learning",
    "Implicit Neural Representation"
  ],
  "links": {
    "openreview": "https://openreview.net/forum?id=CFez7MFUFd",
    "arxiv": null,
    "dblp": null,
    "pdf": "https://openreview.net/pdf/e68b99104a8f0df870e6239dae76778883c81fdf.pdf"
  },
  "citationCount": 0,
  "isHighQuality": false,
  "sections": {
    "method_summary": "Blind image deblurring (BID) is an important yet challenging image recovery problem. Most existing deep learning methods require supervised training with ground truth (GT) images. This paper introduces a self-supervised method for BID that does not require GT images. The key challenge is to regulari"
  },
  "collected_at": "2026-03-10T12:01:28.723Z"
}