{
  "id": "GZoAUVSkaw",
  "or_id": "GZoAUVSkaw",
  "title": "First-Order Minimax Bilevel Optimization",
  "title_zh": "",
  "authors": [
    "Yifan Yang",
    "Zhaofeng Si",
    "Siwei Lyu",
    "Kaiyi Ji"
  ],
  "conference": "NeurIPS",
  "year": 2024,
  "venue": "NeurIPS 2024 poster",
  "abstract": "Multi-block minimax bilevel optimization has been studied recently due to its great potential in multi-task learning, robust machine learning, and few-shot learning. However, due to the complex three-level optimization structure, existing algorithms often suffer from issues such as high computing costs due to the second-order model derivatives or high memory consumption in storing all blocks' parameters. In this paper, we tackle these challenges by proposing two novel fully first-order algorithms named FOSL and MemCS. FOSL features a fully single-loop structure by updating all three variables simultaneously, and MemCS is a memory-efficient double-loop algorithm with cold-start initialization. We provide a comprehensive convergence analysis for both algorithms under full and partial block participation, and show that their sample complexities match or outperform those of the same type of methods in standard bilevel optimization. We evaluate our methods in two applications: the recently proposed multi-task deep AUC maximization and a novel rank-based robust meta-learning. Our methods consistently improve over existing methods with better performance over various datasets.",
  "abstract_zh": "",
  "tldr": "",
  "keywords": [
    "Bilevel Optimization",
    "Machine Learning",
    "Meta Learning"
  ],
  "links": {
    "openreview": "https://openreview.net/forum?id=GZoAUVSkaw",
    "arxiv": null,
    "dblp": null,
    "pdf": "https://openreview.net/pdf/50827d183e9d283c204e1c4fb7696727a4b887a5.pdf"
  },
  "citationCount": 0,
  "isHighQuality": false,
  "sections": {
    "method_summary": "Multi-block minimax bilevel optimization has been studied recently due to its great potential in multi-task learning, robust machine learning, and few-shot learning. However, due to the complex three-level optimization structure, existing algorithms often suffer from issues such as high computing co"
  },
  "collected_at": "2026-03-10T13:01:26.026Z"
}