{
  "id": "J2wI2rCG2u",
  "or_id": "J2wI2rCG2u",
  "title": "Stochastic Taylor Derivative Estimator: Efficient amortization for arbitrary differential operators",
  "title_zh": "",
  "authors": [
    "Zekun Shi",
    "Zheyuan Hu",
    "Min Lin",
    "Kenji Kawaguchi"
  ],
  "conference": "NeurIPS",
  "year": 2024,
  "venue": "NeurIPS 2024 oral",
  "abstract": "Optimizing neural networks with loss that contain high-dimensional and high-order differential operators\n  is expensive to evaluate with back-propagation due to $\\mathcal{O}(d^{k})$ scaling of the derivative tensor size and the $\\mathcal{O}(2^{k-1}L)$ scaling in the computation graph, where $d$ is the dimension of the domain, $L$ is the number of ops in the forward computation graph, and $k$ is the derivative order. In previous works, the polynomial scaling in $d$ was addressed by amortizing the computation over the optimization process via randomization. Separately, the exponential scaling in $k$ for univariate functions ($d=1$) was addressed with high-order auto-differentiation (AD). In this work, we show how to efficiently perform arbitrary contraction of the derivative tensor of arbitrary order for multivariate functions, by properly constructing the input tangents to univariate high-order AD, which can be used to efficiently randomize any differential operator.\n  When applied to Physics-Informed Neural Networks (PINNs), our method provides >1000$\\times$ speed-up and >30$\\times$ memory reduction over randomization with first-order AD, and we can now solve 1-million-dimensional PDEs in 8 minutes on a single NVIDIA A100 GPU. This work opens the possibility of using high-order differential operators in large-scale problems.",
  "abstract_zh": "",
  "tldr": "",
  "keywords": [
    "AI for Science",
    "Automatic Differentiation",
    "Deep Learning",
    "Randomization"
  ],
  "links": {
    "openreview": "https://openreview.net/forum?id=J2wI2rCG2u",
    "arxiv": null,
    "dblp": null,
    "pdf": "https://openreview.net/pdf/8df82199f3b7e09ca3d98f528bb665d7c735933d.pdf"
  },
  "citationCount": 0,
  "isHighQuality": true,
  "sections": {
    "note": "Detailed extraction pending",
    "method_summary": "Optimizing neural networks with loss that contain high-dimensional and high-order differential operators\n  is expensive to evaluate with back-propagation due to $\\mathcal{O}(d^{k})$ scaling of the derivative tensor size and the $\\mathcal{O}(2^{k-1}L)$ scaling in the computation graph, where $d$ is the dimension of the domain, $L$ is the number of ops in the forward computation graph, and $k$ is th"
  },
  "collected_at": "2026-03-07T22:22:02.058Z"
}