{
  "id": "jYypS5VIPj",
  "or_id": "jYypS5VIPj",
  "title": "Bridge the Points: Graph-based Few-shot Segment Anything Semantically",
  "title_zh": "",
  "authors": [
    "Anqi Zhang",
    "Guangyu Gao",
    "Jianbo Jiao",
    "Chi Harold Liu",
    "Yunchao Wei"
  ],
  "conference": "NeurIPS",
  "year": 2024,
  "venue": "NeurIPS 2024 spotlight",
  "abstract": "The recent advancements in large-scale pre-training techniques have significantly enhanced the capabilities of vision foundation models, notably the Segment Anything Model (SAM), which can generate precise masks based on point and box prompts. Recent studies extend SAM to Few-shot Semantic Segmentation (FSS), focusing on prompt generation for SAM-based automatic semantic segmentation. However, these methods struggle with selecting suitable prompts, require specific hyperparameter settings for different scenarios, and experience prolonged one-shot inference times due to the overuse of SAM, resulting in low efficiency and limited automation ability. To address these issues, we propose a simple yet effective approach based on graph analysis. In particular, a Positive-Negative Alignment module dynamically selects the point prompts for generating masks, especially uncovering the potential of the background context as the negative reference. Another subsequent Point-Mask Clustering module aligns the granularity of masks and selected points as a directed graph, based on mask coverage over points. These points are then aggregated by decomposing the weakly connected components of the directed graph in an efficient manner, constructing distinct natural clusters. Finally, the positive and overshooting gating, benefiting from graph-based granularity alignment, aggregates high-confident masks and filters the false-positive masks for final prediction, reducing the usage of additional hyperparameters and redundant mask generation. Extensive experimental analysis across standard FSS, One-shot Part Segmentation, and Cross Domain FSS datasets validate the effectiveness and efficiency of the proposed approach, surpassing state-of-the-art generalist models with a mIoU of 58.7% on COCO-20i and 35.2% on LVIS-92i. The project page of this work is https://andyzaq.github.io/GF-SAM/.",
  "abstract_zh": "",
  "tldr": "",
  "keywords": [
    "semantic segmentation; few shot; Segment Anything Model; Parameter-Free;"
  ],
  "links": {
    "openreview": "https://openreview.net/forum?id=jYypS5VIPj",
    "arxiv": null,
    "dblp": null,
    "pdf": "https://openreview.net/pdf/079fc6b64dad865cb98866238ab263d437333a2c.pdf"
  },
  "citationCount": 0,
  "isHighQuality": true,
  "sections": {
    "note": "Detailed extraction pending",
    "method_summary": "The recent advancements in large-scale pre-training techniques have significantly enhanced the capabilities of vision foundation models, notably the Segment Anything Model (SAM), which can generate precise masks based on point and box prompts. Recent studies extend SAM to Few-shot Semantic Segmentation (FSS), focusing on prompt generation for SAM-based automatic semantic segmentation. However, the"
  },
  "collected_at": "2026-03-10T15:21:35.642Z"
}