{
  "id": "kREpCQtHdN",
  "or_id": "kREpCQtHdN",
  "title": "Identifying Latent State-Transition Processes for Individualized Reinforcement Learning",
  "title_zh": "",
  "authors": [
    "Yuewen Sun",
    "Biwei Huang",
    "Yu Yao",
    "Donghuo Zeng",
    "Xinshuai Dong",
    "Songyao Jin",
    "Boyang Sun",
    "Roberto Legaspi",
    "Kazushi Ikeda",
    "Peter Spirtes",
    "Kun Zhang"
  ],
  "conference": "NeurIPS",
  "year": 2024,
  "venue": "NeurIPS 2024 poster",
  "abstract": "The application of reinforcement learning (RL) involving interactions with individuals has grown significantly in recent years. These interactions, influenced by factors such as personal preferences and physiological differences, causally influence state transitions, ranging from health conditions in healthcare to learning progress in education. As a result, different individuals may exhibit different state-transition processes. Understanding individualized state-transition processes is essential for optimizing individualized policies. In practice, however, identifying these state-transition processes is challenging, as individual-specific factors often remain latent. In this paper, we establish the identifiability of these latent factors and introduce a practical method that effectively learns these processes from observed state-action trajectories. Experiments on various datasets show that the proposed method can effectively identify latent state-transition processes and facilitate the learning of individualized RL policies.",
  "abstract_zh": "",
  "tldr": "",
  "keywords": [
    "Reinforcement Learning",
    "Identifiability",
    "Individualization"
  ],
  "links": {
    "openreview": "https://openreview.net/forum?id=kREpCQtHdN",
    "arxiv": null,
    "dblp": null,
    "pdf": "https://openreview.net/pdf/c647ba82ceef44f9b60644936da1ec2daade0bd7.pdf"
  },
  "citationCount": 0,
  "isHighQuality": false,
  "sections": {
    "method_summary": "The application of reinforcement learning (RL) involving interactions with individuals has grown significantly in recent years. These interactions, influenced by factors such as personal preferences and physiological differences, causally influence state transitions, ranging from health conditions i"
  },
  "collected_at": "2026-03-08T05:22:10.682Z"
}