{
  "id": "nExI4FuKWD",
  "or_id": "nExI4FuKWD",
  "title": "FineCLIP: Self-distilled Region-based CLIP for Better Fine-grained Understanding",
  "title_zh": "",
  "authors": [
    "Dong Jing",
    "Xiaolong He",
    "Yutian Luo",
    "Nanyi Fei",
    "Guoxing Yang",
    "Wei Wei",
    "Huiwen Zhao",
    "Zhiwu Lu"
  ],
  "conference": "NeurIPS",
  "year": 2024,
  "venue": "NeurIPS 2024 poster",
  "abstract": "Contrastive Language-Image Pre-training (CLIP) achieves impressive performance on tasks like image classification and image-text retrieval by learning on large-scale image-text datasets. However, CLIP struggles with dense prediction tasks due to the poor grasp of the fine-grained details. Although existing works pay attention to this issue, they achieve limited improvements and usually sacrifice the important visual-semantic consistency. To overcome these limitations, we propose FineCLIP, which keeps the global contrastive learning to preserve the visual-semantic consistency and further enhances the fine-grained understanding through two innovations: 1) A real-time self-distillation scheme that facilitates the transfer of representation capability from global to local features. 2) A semantically-rich regional contrastive learning paradigm with generated region-text pairs, boosting the local representation capabilities with abundant fine-grained knowledge. \nBoth cooperate to fully leverage diverse semantics and multi-grained complementary information.\nTo validate the superiority of our FineCLIP and the rationality of each design, we conduct extensive experiments on challenging dense prediction and image-level tasks. \nAll the observations demonstrate the effectiveness of FineCLIP.",
  "abstract_zh": "",
  "tldr": "",
  "keywords": [
    "CLIP",
    "Fine-grained Understanding"
  ],
  "links": {
    "openreview": "https://openreview.net/forum?id=nExI4FuKWD",
    "arxiv": null,
    "dblp": null,
    "pdf": "https://openreview.net/pdf/e77b9bf69974b22ae77ee4209dc907d97148cbdd.pdf"
  },
  "citationCount": 0,
  "isHighQuality": false,
  "sections": {
    "method_summary": "Contrastive Language-Image Pre-training (CLIP) achieves impressive performance on tasks like image classification and image-text retrieval by learning on large-scale image-text datasets. However, CLIP struggles with dense prediction tasks due to the poor grasp of the fine-grained details. Although e"
  },
  "collected_at": "2026-03-08T00:41:58.051Z"
}