{
  "id": "Px1hQM72iX",
  "or_id": "Px1hQM72iX",
  "title": "Density-based User Representation using Gaussian Process Regression for Multi-interest Personalized Retrieval",
  "title_zh": "",
  "authors": [
    "Haolun Wu",
    "Ofer Meshi",
    "Masrour Zoghi",
    "Fernando Diaz",
    "Xue Liu",
    "Craig Boutilier",
    "MARYAM KARIMZADEHGAN"
  ],
  "conference": "NeurIPS",
  "year": 2024,
  "venue": "NeurIPS 2024 poster",
  "abstract": "Accurate modeling of the diverse and dynamic interests of users remains a significant challenge in the design of personalized recommender systems. Existing user modeling methods, like single-point and multi-point representations, have limitations w.r.t.\\ accuracy, diversity, and adaptability. To overcome these deficiencies, we introduce density-based user representations (DURs), a novel method that leverages Gaussian process regression (GPR) for effective multi-interest recommendation and retrieval. Our approach, GPR4DUR, exploits DURs to capture user interest variability without manual tuning, incorporates uncertainty-awareness, and scales well to large numbers of users. Experiments using real-world offline datasets confirm the adaptability and efficiency of GPR4DUR, while online experiments with simulated users demonstrate its ability to address the exploration-exploitation trade-off by effectively utilizing model uncertainty.",
  "abstract_zh": "",
  "tldr": "",
  "keywords": [
    "User Representation",
    "Recommendation",
    "Retrieval",
    "Gaussian Process Regression"
  ],
  "links": {
    "openreview": "https://openreview.net/forum?id=Px1hQM72iX",
    "arxiv": null,
    "dblp": null,
    "pdf": "https://openreview.net/pdf/6fcc2fb80f8768e72d83fd0a25391e91b6872df1.pdf"
  },
  "citationCount": 0,
  "isHighQuality": false,
  "sections": {
    "method_summary": "Accurate modeling of the diverse and dynamic interests of users remains a significant challenge in the design of personalized recommender systems. Existing user modeling methods, like single-point and multi-point representations, have limitations w.r.t.\\ accuracy, diversity, and adaptability. To ove"
  },
  "collected_at": "2026-03-08T03:42:06.582Z"
}