{
  "id": "Qk3IBHyv6z",
  "or_id": "Qk3IBHyv6z",
  "title": "Multi-Agent Imitation Learning: Value is Easy, Regret is Hard",
  "title_zh": "",
  "authors": [
    "Jingwu Tang",
    "Gokul Swamy",
    "Fei Fang",
    "Steven Wu"
  ],
  "conference": "NeurIPS",
  "year": 2024,
  "venue": "NeurIPS 2024 poster",
  "abstract": "We study a multi-agent imitation learning (MAIL) problem where we take the perspective of a learner attempting to *coordinate* a group of agents based on demonstrations of an expert doing so. Most prior work in MAIL essentially reduces the problem to matching the behavior of the expert *within* the support of the demonstrations. While doing so is sufficient to drive the *value gap* between the learner and the expert to zero under the assumption that agents are non-strategic, it does not guarantee robustness to deviations by strategic agents. Intuitively, this is because strategic deviations can depend on a counterfactual quantity: the coordinator's recommendations outside of the state distribution their recommendations induce. In response, we initiate the study of an alternative objective for MAIL in Markov Games we term the *regret gap* that explicitly accounts for potential deviations by agents in the group. We first perform an in-depth exploration of the relationship between the value and regret gaps. First, we show that while the value gap can be efficiently minimized via a direct extension of single-agent IL algorithms, even *value equivalence* can lead to an arbitrarily large regret gap. This implies that achieving regret equivalence is harder than achieving value equivalence in MAIL. We then provide a pair of efficient reductions to no-regret online convex optimization that are capable of minimizing the regret gap *(a)* under a coverage assumption on the expert (MALICE) or *(b)* with access to a queryable expert (BLADES).",
  "abstract_zh": "",
  "tldr": "",
  "keywords": [
    "imitation learning",
    "multi-agent reinforcement learning"
  ],
  "links": {
    "openreview": "https://openreview.net/forum?id=Qk3IBHyv6z",
    "arxiv": null,
    "dblp": null,
    "pdf": "https://openreview.net/pdf/85c274327fc673a249af4459e7b9afd62b81b79d.pdf"
  },
  "citationCount": 0,
  "isHighQuality": false,
  "sections": {
    "method_summary": "We study a multi-agent imitation learning (MAIL) problem where we take the perspective of a learner attempting to *coordinate* a group of agents based on demonstrations of an expert doing so. Most prior work in MAIL essentially reduces the problem to matching the behavior of the expert *within* the "
  },
  "collected_at": "2026-03-09T03:45:13.527Z"
}