{
  "id": "SKCbZR8Pyd",
  "or_id": "SKCbZR8Pyd",
  "title": "SpeechAlign: Aligning Speech Generation to Human Preferences",
  "title_zh": "",
  "authors": [
    "Dong Zhang",
    "Zhaowei Li",
    "Shimin Li",
    "Xin Zhang",
    "Pengyu Wang",
    "Yaqian Zhou",
    "Xipeng Qiu"
  ],
  "conference": "NeurIPS",
  "year": 2024,
  "venue": "NeurIPS 2024 poster",
  "abstract": "Speech language models have significantly advanced in generating realistic speech, with neural codec language models standing out. However, the integration of preference optimization to align speech outputs to human preferences is often neglected. This paper addresses this gap by first analyzing the distribution gap in codec language models, highlighting how it leads to discrepancies between the training and inference phases, which negatively affects performance. Then we explore leveraging preference optimization to bridge the distribution gap. We introduce SpeechAlign, an iterative self-improvement strategy that aligns speech language models to human preferences.  SpeechAlign involves constructing a preference codec dataset contrasting golden codec tokens against synthetic tokens, followed by preference optimization to improve the codec language model. This cycle of improvement is carried out iteratively to steadily convert weak models to strong ones. Through both subjective and objective evaluations, we show that SpeechAlign can bridge the distribution gap and facilitating continuous self-improvement of the speech language model. Moreover, SpeechAlign exhibits robust generalization capabilities and works for smaller models.  Demos are available at https://0nutation.github.io/SpeechAlign.github.io/.",
  "abstract_zh": "",
  "tldr": "",
  "keywords": [
    "Speech generation",
    "RLHF",
    "self-improvement"
  ],
  "links": {
    "openreview": "https://openreview.net/forum?id=SKCbZR8Pyd",
    "arxiv": null,
    "dblp": null,
    "pdf": "https://openreview.net/pdf/5be49395a83725680ce034c52f056414051b592f.pdf"
  },
  "citationCount": 0,
  "isHighQuality": false,
  "sections": {
    "method_summary": "Speech language models have significantly advanced in generating realistic speech, with neural codec language models standing out. However, the integration of preference optimization to align speech outputs to human preferences is often neglected. This paper addresses this gap by first analyzing the"
  },
  "collected_at": "2026-03-07T18:40:30.646Z"
}