{
  "id": "SYjxhKcXoN",
  "or_id": "SYjxhKcXoN",
  "title": "LFME: A Simple Framework for Learning from Multiple Experts in Domain Generalization",
  "title_zh": "",
  "authors": [
    "Liang Chen",
    "Yong Zhang",
    "Yibing Song",
    "Zhiqiang Shen",
    "Lingqiao Liu"
  ],
  "conference": "NeurIPS",
  "year": 2024,
  "venue": "NeurIPS 2024 poster",
  "abstract": "Domain generalization (DG) methods aim to maintain good performance in an unseen target domain by using training data from multiple source domains. While success on certain occasions are observed, enhancing the baseline across most scenarios remains challenging. This work introduces a simple yet effective framework, dubbed learning from multiple experts (LFME), that aims to make the target model an expert in all source domains to improve DG. Specifically, besides learning the target model used in inference, LFME will also train multiple experts specialized in different domains, whose output probabilities provide professional guidance by simply regularizing the logit of the target model. Delving deep into the framework, we reveal that the introduced logit regularization term implicitly provides effects of enabling the target model to harness more information, and mining hard samples from the experts during training. Extensive experiments on benchmarks from different DG tasks demonstrate that LFME is consistently beneficial to the baseline and can achieve comparable performance to existing arts.  Code is available at https://github.com/liangchen527/LFME.",
  "abstract_zh": "",
  "tldr": "A new knowledge distillation paradigm to enable effective learning from multiple experts for domain generalization",
  "keywords": [
    "Domain generalization",
    "Knowledge distillation"
  ],
  "links": {
    "openreview": "https://openreview.net/forum?id=SYjxhKcXoN",
    "arxiv": null,
    "dblp": null,
    "pdf": "https://openreview.net/pdf/abdbf557f3ef17f902813f735892688ad6e31888.pdf"
  },
  "citationCount": 0,
  "isHighQuality": false,
  "sections": {
    "method_summary": "A new knowledge distillation paradigm to enable effective learning from multiple experts for domain generalization"
  },
  "collected_at": "2026-03-08T06:02:04.022Z"
}