{
  "id": "yfQwyxiSJ7",
  "or_id": "yfQwyxiSJ7",
  "title": "Color-Oriented Redundancy Reduction in Dataset Distillation",
  "title_zh": "",
  "authors": [
    "Bowen Yuan",
    "Zijian Wang",
    "Mahsa Baktashmotlagh",
    "Yadan Luo",
    "Zi Huang"
  ],
  "conference": "NeurIPS",
  "year": 2024,
  "venue": "NeurIPS 2024 poster",
  "abstract": "Dataset Distillation (DD) is designed to generate condensed representations of extensive image datasets, enhancing training efficiency. Despite recent advances, there remains considerable potential for improvement, particularly in addressing the notable redundancy within the color space of distilled images. In this paper, we propose a two-fold optimization strategy to minimize color redundancy at the individual image and overall dataset levels, respectively. At the image level, we employ a palette network, a specialized neural network, to dynamically allocate colors from a reduced color space to each pixel. The palette network identifies essential areas in synthetic images for model training, and consequently assigns more unique colors to them. At the dataset level, we develop a color-guided initialization strategy to minimize redundancy among images. Representative images with the least replicated color patterns are selected based on the information gain. A comprehensive performance study involving various datasets and evaluation scenarios is conducted, demonstrating the superior performance of our proposed color-aware DD compared to existing DD methods.",
  "abstract_zh": "",
  "tldr": "A novel parameterization method for data distillation by exploring the redundancy in color space.",
  "keywords": [
    "Computer Vision",
    "Data Distillation",
    "Parameterization"
  ],
  "links": {
    "openreview": "https://openreview.net/forum?id=yfQwyxiSJ7",
    "arxiv": null,
    "dblp": null,
    "pdf": "https://openreview.net/pdf/20b534cf5fff43e4e9a8229eb66f4841e6dba9df.pdf"
  },
  "citationCount": 0,
  "isHighQuality": false,
  "sections": {
    "method_summary": "A novel parameterization method for data distillation by exploring the redundancy in color space."
  },
  "collected_at": "2026-03-10T14:01:40.511Z"
}