{
  "id": "YwpL0BVxts",
  "or_id": "YwpL0BVxts",
  "title": "United We Stand, Divided We Fall: Fingerprinting Deep Neural Networks via Adversarial Trajectories",
  "title_zh": "",
  "authors": [
    "Tianlong Xu",
    "Chen Wang",
    "Gaoyang Liu",
    "Yang Yang",
    "Kai Peng",
    "Wei Liu"
  ],
  "conference": "NeurIPS",
  "year": 2024,
  "venue": "NeurIPS 2024 poster",
  "abstract": "In recent years, deep neural networks (DNNs) have witnessed extensive applications, and protecting their intellectual property (IP) is thus crucial. As a non-invasive way for model IP protection, model fingerprinting has become popular. However, existing single-point based fingerprinting methods are highly sensitive to the changes in the decision boundary, and may suffer from the misjudgment of the resemblance of sparse fingerprinting, yielding high false positives of innocent models. In this paper, we propose ADV-TRA, a more robust fingerprinting scheme that utilizes adversarial trajectories to verify the ownership of DNN models. Benefited from the intrinsic progressively adversarial level, the trajectory is capable of tolerating greater degree of alteration in decision boundaries. We further design novel schemes to generate a surface trajectory that involves a series of fixed-length trajectories with dynamically adjusted step sizes. Such a design enables a more unique and reliable fingerprinting with relatively low querying costs. Experiments on three datasets against four types of removal attacks show that ADV-TRA exhibits superior performance in distinguishing between infringing and innocent models, outperforming the state-of-the-art comparisons.",
  "abstract_zh": "",
  "tldr": "",
  "keywords": [
    "Deep neural network",
    "intellectual property protection",
    "model fingerprinting",
    "adversarial sample."
  ],
  "links": {
    "openreview": "https://openreview.net/forum?id=YwpL0BVxts",
    "arxiv": null,
    "dblp": null,
    "pdf": "https://openreview.net/pdf/c4e326e4220480b60f51e63ae149d2009d4cccd5.pdf"
  },
  "citationCount": 0,
  "isHighQuality": false,
  "sections": {
    "method_summary": "In recent years, deep neural networks (DNNs) have witnessed extensive applications, and protecting their intellectual property (IP) is thus crucial. As a non-invasive way for model IP protection, model fingerprinting has become popular. However, existing single-point based fingerprinting methods are"
  },
  "collected_at": "2026-03-10T14:21:35.766Z"
}