{
  "id": "hujS6bmduD",
  "or_id": "hujS6bmduD",
  "title": "Harnessing Text to Image Diffusion for Dense Prediction Tasks",
  "title_zh": "",
  "authors": [
    "Yiqi Wang",
    "Quanzeng You",
    "Wentao Chen",
    "Bin Shan",
    "Jianbo Yuan",
    "Yingjie Tian",
    "Hongxia Yang"
  ],
  "conference": "ICLR",
  "year": 2024,
  "venue": "ICLR 2024 Conference Withdrawn Submission",
  "abstract": "Equipped with large-scale training data, text-to-image diffusion models have demonstrated the capacity to generate high-quality images that semantically correspond to the given textual descriptions. \nThese compelling results imply that visual semantic knowledge has been effectively encapsulated within the generative diffusion model. \nThe prospect of utilizing this embedded knowledge as a prior for down-stream vision tasks presents an intriguing avenue for exploration, which remains notably under-investigated. In this work, we demonstrate that when provided with appropriate image tags as textual descriptions, the implicit knowledge within these text-to-image diffusion models can be effectively leveraged for visual dense prediction tasks. Initially, we discover that supplying ground-truth semantic labels as textual instructions significantly enhances performance due to the extracted high-quality visual knowledge. Motivated by this observation, when presented with noisy tagging labels, we propose an adapter module attempting to derive relevant semantic information.\nSubsequently, we propose a multi-label classification learning objective which further enriches the semantic quality of tags, thereby amplifying the efficacy of knowledge extraction.  We conduct extensive experiments four benchmarks, which suggest that the proposed approach is effective to unlock the representational capabilities of text-to-image diffusion models, showcasing a promising avenue for advancing dense prediction tasks in visual domains.",
  "abstract_zh": "",
  "tldr": "",
  "keywords": [
    "Diffusion Models;Visual Perception; Class Captioner"
  ],
  "links": {
    "openreview": "https://openreview.net/forum?id=hujS6bmduD",
    "arxiv": null,
    "dblp": null,
    "pdf": "https://openreview.net/pdf/92e683ed1ef597ce05f0b0aad6ee3fadbbeedb81.pdf"
  },
  "citationCount": 0,
  "isHighQuality": false,
  "sections": {
    "method_summary": "Equipped with large-scale training data, text-to-image diffusion models have demonstrated the capacity to generate high-quality images that semantically correspond to the given textual descriptions. \nThese compelling results imply that visual semantic knowledge has been effectively encapsulated with"
  },
  "collected_at": "2026-03-07T16:40:53.330Z"
}