{
  "id": "lLhEQWQYtb",
  "or_id": "lLhEQWQYtb",
  "title": "Parameter Estimation of Long Memory Stochastic Processes with Deep Neural Networks",
  "title_zh": "",
  "authors": [
    "Balint Csanady",
    "Lóránt Nagy",
    "Dávid Kovács",
    "Daniel Boros",
    "Ivan Ivkovic",
    "Dalma Tóth-Lakits",
    "Laszlo Markus",
    "András Lukács"
  ],
  "conference": "ICLR",
  "year": 2024,
  "venue": "Submitted to ICLR 2024",
  "abstract": "We present a pure deep neural network-based approach for estimating long memory parameters of time series models that incorporate the phenomenon of long range dependence. Long memory parameters such as the Hurst exponent are critical in characterizing the long-range dependence, roughness, and self-similarity of stochastic processes. The accurate and fast estimation of these parameters is of paramount importance in various scientific fields, including finance, physics, and engineering. We harnessed efficient process generators to provide high-quality synthetic training data to train 1D Convolutional Neural Network (CNN) and Long Short-Term Memory (LSTM) models. Our neural models outperform conventional statistical methods, even if the latter have neural network extensions. Precision, speed as well as consistency and robustness of the estimators are supported by experiments with fractional Brownian motion (fBm), the Autoregressive Fractionally Integrated Moving Average (ARFIMA) process, and the fractional Ornstein-Uhlenbeck process (fOU). We believe that our work will inspire further research in the application of deep learning techniques for stochastic process modeling and parameter estimation.",
  "abstract_zh": "",
  "tldr": "Deep neural networks for better Hurst exponent estimation in the cases of various stochastic processes.",
  "keywords": [
    "Hurst parameter",
    "Fractional Brownian motion",
    "ARFIMA",
    "Fractional Ornstein-Uhlenbeck processes",
    "1D convolutional neural networks",
    "LSTM"
  ],
  "links": {
    "openreview": "https://openreview.net/forum?id=lLhEQWQYtb",
    "arxiv": null,
    "dblp": null,
    "pdf": "https://openreview.net/pdf/72771de84ed45e0dd594c155a8a2a5a887afad97.pdf"
  },
  "citationCount": 0,
  "isHighQuality": false,
  "sections": {
    "method_summary": "Deep neural networks for better Hurst exponent estimation in the cases of various stochastic processes."
  },
  "collected_at": "2026-03-15T18:31:12.579Z"
}